{
"Волонтерська допомога": ["Допомога літнім людям", "Транспортні перевезення", "Доставка пального", "Надання або пошук житла", "Доставка їжі", "Доставка медикаментів", "Психологічна допомога", "Допомога тваринам"],
"Кур'єрські послуги": ["Кур'єрська доставка", "Доставка продуктів", "Доставка готової їжі", "Доставка ліків", "Кур'єр на авто", "Доставка товару з інтернет-магазину", "Доставка документів", "Доставка подарунків", "Доставка квітів", "Відправити поїздом або маршруткою", "Забрати і відправити поштою", "Знайти", "Постояти в черзі", "Інші кур'єрські послуги"],
"Клінінгові послуги": ["Прибирання квартир", "Генеральне прибирання", "Прибирання після ремонту", "Хімчистка меблів", "Хімчистка килимів", "Хімчистка одягу", "Хімчистка текстилю", "Хімчистка хутряних виробів", "Хімчистка шкіряних виробів", "Інше в послугах хімчистки", "Прибирання котеджів і будинків", "Мийка вікон", "Миття фасадів", "Еко-прибирання", "Прибирання офісів", "Прибирання ресторанів", "Прибирання магазинів", "Прибирання прилеглих територій", "Дезінсекція", "Дезінфекція приміщень", "Дератизація", "Озонування приміщень", "Прибирання після потопів і пожеж", "Прибирання виробничих приміщень", "Організація простору", "Інше прибирання"],
"Домашній майстер": ["Онлайн консультація сантехніка", "Сантехнічні роботи", "Усунення протікання води", "Установка і ремонт унітазів", "Прочищення каналізації", "Установка і ремонт змішувача", "Установка і ремонт крана", "Монтаж і ремонт водопроводу", "Установка і ремонт душової кабіни", "Установка і заміна радіаторів", "Реставрація ванн", "Установка і заміна фільтрів для води", "Встановлення і заміна сифона", "Установка і ремонт раковини", "Монтаж каналізації", "Установка і заміна сушки для рушників", "Врізка та встановлення мийки", "Установка і заміна лічильників води", "Установка ванни", "Інші послуги сантехніка", "Монтаж і ремонт електропроводки", "Установка і ремонт світильників", "Підключення та ремонт люстри", "Установка і заміна розеток", "Електромонтажні роботи", "Монтаж і заміна вимикача", "Установка домофона", "Установка ПЗВ і автоматів", "Підключення стабілізатора напруги", "Штроблення стін", "Установка і заміна електролічильника", "Установка дзвінка", "Установка і заміна трансформатора", "Монтаж і збірка електрощита", "Інші послуги електрика", "Аварійне відкриття замків", "Установка замків", "Ремонт замків", "Встановлення жалюзі", "Свердління отворів", "Установка карниза", "Установка дзеркал", "Установка полиць", "Монтаж стельової сушарки", "Інші послуги чоловіка на годину", "Столяр", "Слюсар", "Установка телевізора", "Встановлення пральної машини", "Установка витяжки", "Установка кондиціонерів", "Установка посудомийної машини", "Установка газової плити", "Встановлення газового котла", "Встановлення газової колонки", "Установка варильної поверхні", "Установка бойлера", "Установка духової шафи", "Встановлення електроплити", "Установка сушильної машини", "Установка вбудованого холодильника", "Установка подрібнювача відходів", "Встановлення іншої побутової техніки", "Інші послуги майстра"],
"Транспортні та складські послуги": ["Вантажні перевезення", "Послуги вантажників", "Вивіз будівельного сміття", "Перевезення меблів і техніки", "Переїзд квартири або офісу", "Послуги таксі", "Тверезий водій", "Пасажирські перевезення", "Міжміські перевезення", "Упаковка і сортування", "Послуги складу", "Міжнародні перевезення", "Вивіз снігу", "Митне оформлення", "Послуги експедитора", "Інші логістичні та складські послуги"],
"Меблеві роботи": ["Виготовлення полиць", "Виготовлення тумб", "Виготовлення кухонних меблів", "Виготовлення стелажів", "Виготовлення шаф-купе", "Виготовлення гардеробних", "Виготовлення столів", "Виготовлення стільців", "Виготовлення диванів", "Виготовлення ліжок", "Виготовлення офісних меблів", "Виготовлення меблів з піддонів", "Виготовлення дитячих меблів", "Виготовлення передпокоїв", "Виготовлення інших меблів", "Ремонт кухонних меблів", "Ремонт шаф", "Ремонт диванів", "Ремонт ліжок", "Ремонт ящиків і полиць", "Ремонт стільців", "Ремонт столів", "Заміна наповнювача", "Ремонт інших меблів", "Складання кухні", "Складання шаф", "Складання столів", "Складання ліжок", "Складання комодів", "Складання стелажів", "Складання крісел", "Складання диванів", "Складання тумбочок", "Складання гардеробної", "Складання інших меблів", "Реставрація меблів", "Перетяжка меблів", "Складання кухні IKEA", "Складання гардеробної IKEA", "Складання шаф IKEA", "Складання меблів для ванної IKEA", "Складання ліжок IKEA", "Складання столів IKEA", "Складання крісел IKEA", "Складання диванів IKEA", "Складання комодів IKEA", "Складання стелажів IKEA", "Складання тумб IKEA", "Складання дитячих меблів IKEA", "Складання стільців IKEA", "Складання інших меблів IKEA", "Швачка м'яких меблів", "Інші меблеві роботи"],
"Ремонт техніки": ["Ремонт великої побутової техніки", "Ремонт пральних машин", "Ремонт холодильників", "Ремонт посудомийних машин", "Ремонт бойлерів", "Ремонт кондиціонерів", "Ремонт газових плит", "Ремонт електричних духовок", "Ремонт мікрохвильовок", "Ремонт варильних панелей", "Ремонт електроплит", "Ремонт витяжок", "Ремонт пилососів", "Ремонт газових колонок", "Ремонт газового котла", "Ремонт сушильних машин", "Ремонт електричного котла", "Ремонт парогенераторів", "Ремонт морозильних камер", "Ремонт подрібнювачів відходів", "Інший ремонт великої побутової техніки", "Ремонт дрібної побутової техніки", "Ремонт кавоварок", "Ремонт швейних машин", "Ремонт блендерів і міксерів", "Ремонт мультиварок", "Ремонт обігрівачів", "Ремонт ваг", "Ремонт прасок", "Ремонт кухонних комбайнів", "Ремонт електрочайників", "Ремонт зволожувачів повітря", "Ремонт вентиляторів", "Ремонт хлібопічок", "Ремонт фритюрниць", "Ремонт тостерів", "Ремонт м'ясорубок", "Ремонт соковижималок", "Інший ремонт дрібної побутової техніки", "Комп'ютерна допомога", "Ремонт ноутбуків", "Установка Windows", "Встановлення та налаштування програм", "Ремонт комп'ютерів", "Ремонт комплектуючих", "Підключення і настройка Інтернету", "Налаштування Wi-Fi", "Видалення вірусів", "Відновлення даних", "Чистка від пилу", "Діагностика ноутбуків і ПК", "Встановлення і налаштування серверів", "Ремонт моніторів", "Інший ремонт ноутбуків і ПК", "Ремонт цифрової техніки", "Ремонт телевізорів", "Ремонт навушників", "Ремонт смарт-годинників", "Ремонт повербанків", "Ремонт аудіосистем", "Ремонт автомагнітол", "Ремонт ігрових приставок", "Ремонт фотоапаратів", "Ремонт планшетів", "Ремонт підсилювачів", "Ремонт відео і радіоняні", "Ремонт відеореєстраторів", "Ремонт UPS безперебійника", "Ремонт MP3 плеєрів", "Ремонт GPS навігаторів", "Ремонт електронних книг", "Ремонт відеокамер", "Ремонт DVD плеєрів", "Інший ремонт цифрової техніки", "Ремонт мобільних телефонів", "Ремонт iPhone", "Ремонт телефонів Samsung", "Ремонт телефонів Xiaomi", "Ремонт телефонів Huawei", "Ремонт телефонів LG", "Ремонт телефонів Sony", "Ремонт телефонів Google Pixel", "Ремонт телефонів HTC", "Ремонт телефонів Meizu", "Ремонт телефонів Realme", "Ремонт телефонів Nokia", "Ремонт телефонів Blackview", "Ремонт телефонів Lenovo", "Ремонт інших телефонів", "Обслуговування техніки", "Обслуговування бойлерів", "Обслуговування пральних машин", "Обслуговування посудомийних машин", "Обслуговування холодильників", "Заправка кондиціонерів", "Обслуговування кондиціонерів", "Інше обслуговування техніки", "Налаштування супутникового ТБ", "Встановлення та налаштування Starlink (Старлінк)", "Встановлення супутникового ТБ", "Ремонт супутникових антен", "Монтаж супутникових антен", "Налаштування тюнера", "Прошивка тюнера", "Інші налаштування супутникового ТБ", "Ремонт оргтехніки", "Заправка картриджів", "Ремонт принтерів", "Ремонт БФП", "Ремонт проєкторів", "Ремонт шредерів", "Ремонт сканерів", "Ремонт факсів", "Інший ремонт оргтехніки", "Ремонт техніки для краси і догляду", "Ремонт фенів", "Ремонт машинок для стрижки", "Ремонт бритв і епіляторів", "Ремонт тренажерів", "Ремонт плойок", "Ремонт приладів для манікюру і педикюру", "Ремонт іншої техніки для краси", "Ремонт електроінструментів", "Ремонт електропил і бензопил", "Ремонт фрезерів", "Ремонт фарбопультів", "Ремонт перфораторів", "Ремонт шуруповертів", "Ремонт болгарок", "Ремонт електродрилів", "Ремонт будівельних фенів", "Ремонт електролобзика", "Інший ремонт електроінструментів", "Ремонт медтехніки", "Ремонт електротранспорту", "Ремонт гіроскутерів", "Ремонт моноколіс", "Ремонт електросамокатів", "Ремонт гіробордів", "Ремонт електровелосипедів", "Ремонт електроскутерів", "Ремонт сігвеїв", "Ремонт іншого електротранспорту", "Ремонт садово-паркової техніки", "Ремонт газонокосарок", "Ремонт мотокіс і тримерів", "Ремонт мотоблоків", "Ремонт насосів", "Ремонт мінітракторів", "Ремонт бензинових генераторів", "Ремонт мотобурів", "Ремонт мийок високого тиску", "Інший ремонт садово-паркової техніки", "Встановлення і ремонт систем безпеки", "Монтаж відеоспостереження", "Встановлення охоронної сигналізації", "Встановлення пожежної сигналізації", "Встановлення систем контролю доступу", "Встановлення системи Розумний будинок", "Встановлення інших систем безпеки", "Інший ремонт техніки"],
"Оздоблювальні роботи": ["Ремонт квартир", "Ремонт під ключ", "Частковий ремонт", "Ремонт балкона", "Косметичний ремонт", "Інший ремонт квартир", "Укладання плитки", "Укладання плитки у ванній", "Укладання плитки на підлогу", "Укладання плитки на стіни", "Укладання декоративної плитки", "Укладання мозаїки", "Укладання тротуарної плитки", "Інше в укладанні плитки", "Штукатурні роботи", "Шпаклівка стін", "Ручна штукатурка", "Шпаклівка стель", "Укоси на вікна", "Машинна штукатурка", "Декоративна штукатурка", "Інші штукатурні роботи", "Утеплення приміщень", "Утеплення фасадів", "Утеплення балкона", "Внутрішнє утеплення", "Інші роботи з утеплення", "Монтаж опалення", "Монтаж гіпсокартону", "Малярні роботи", "Фарбування стін", "Фарбування стель", "Фарбування труб", "Розпис стін", "Фарбування будинку", "Грунтовка поверхонь", "Фарбування вікон", "Фарбування радіаторів опалення", "Інші малярні роботи", "Поклейка шпалер", "Поклейка флізелінових шпалер", "Поклейка паперових шпалер", "Зняття старих шпалер", "Поклейка фотошпалер", "Поклейка вінілових шпалер", "Поклейка багетів", "Фарбування шпалер", "Поклейка шпалер на стелю", "Нанесення рідких шпалер", "Поклейка текстильних шпалер", "Поклейка бамбукових шпалер", "Інше в поклейці шпалер", "Підлогові роботи", "Ремонт підлоги", "Стяжка підлоги", "Укладання лінолеуму", "Укладання і ремонт паркету", "Вирівнювання підлог", "Циклювання підлоги", "Укладання ламінату", "Укладання паркетної дошки", "Монтаж плінтуса", "Наливні підлоги", "Укладання ковроліну", "Монтаж теплої підлоги", "Інші підлогові роботи", "Установка і ремонт дверей", "Ремонт дверей", "Установка міжкімнатних дверей", "Установка вхідних дверей", "Оббивка дверей", "Установка металевих дверей", "Установка складних і розсувних дверей", "Виготовлення дверей", "Інше у встановленні дверей", "Полірування мармуру", "Установка і ремонт вікон", "Ремонт і регулювання вікон", "Установка металопластикових вікон", "Виготовлення вікон", "Скління балкона", "Встановлення підвіконня", "Установка дерев'яних вікон", "Інше у встановленні вікон", "Демонтажні роботи", "Демонтаж будівель", "Демонтаж стін", "Демонтаж дверей", "Демонтаж плитки", "Демонтаж стяжки", "Демонтаж штукатурки", "Фасадні роботи", "Послуги з облицювання фасадів", "Оздоблення і ремонт фасаду", "Фарбування фасаду", "Декоративне оздоблення фасаду", "Інші фасадні роботи", "Стельові роботи", "Натяжні стелі", "Підвісні стелі", "Касетні стелі", "Дзеркальні стелі", "Інші стельові роботи", "Робота зі склом", "Звукоізоляція", "Монтаж вагонки", "Інші ремонтні роботи"],
"Будівельні роботи": ["Різноробочі", "Зварювальні роботи", "Токарні роботи", "Тесляр", "Кладка цегли", "Установка заборів та воріт", "Покрівельні роботи", "Бетонні роботи", "Бурові роботи", "Фундаментні роботи", "Будівництво будинків", "Гідроізоляція", "Будівництво дрібних конструкцій", "Будівництво лазні", "Будівництво гаража", "Будівництво альтанок", "Будівництво печі і каміна", "Будівництво теплиць", "Будівництво сараю", "Будівництво веранди", "Виготовлення та монтаж сходів", "Будівництво мангалів і барбекю", "Будівництво басейнів", "Інші дрібні конструкції", "Ландшафтні роботи", "Ландшафтний дизайн", "Установка автополиву", "Озеленення та благоустрій", "Оформлення та створення газону", "Геодезичні роботи", "Дренажні роботи", "Інші ландшафтні роботи", "Архітектура та проектування", "Складання кошторисів", "Земляні роботи", "Монтаж вентиляції", "Промисловий альпінізм", "Розбір завалів", "Інші будівельні роботи"],
"Побутові послуги": ["Сад і город", "Няні", "Послуги доглядальниці", "Послуги домробітниці", "Послуги швачки", "Пошиття одягу", "Ремонт одягу", "Пошиття текстилю", "Машинна вишивка", "Інші послуги швачки", "Ремонт взуття", "Послуги кухаря", "Прання та прасування речей", "Ремонт сумок", "Ремонт рюкзаків", "Ремонт валіз", "Ремонт жіночих сумок", "Ремонт портфелів", "Інший ремонт сумок", "Фарбування одягу", "Ремонт велосипедів", "Заточення інструментів", "Ремонт ювелірних виробів", "Ремонт годинників", "Інші побутові послуги"],
"Фото- і відео-послуги": ["Фотограф", "Предметна зйомка", "Портретна зйомка", "Весільна фотосесія", "Сімейна фотосесія", "Фотозйомка заходів", "Дитяча фотосесія", "Репортажна зйомка", "Інтер'єрна зйомка", "Фотосесія Love Story", "Фотосесія вагітних", "Інше в послугах фотографа", "Відеооператор", "Обробка фотографій", "Монтаж відео", "Оцифровка відеокасет", "Аерозйомка", "Випускні альбоми", "Інші послуги фото і відео"],
"Дизайн": ["Розробка логотипів", "Дизайн інтер'єру", "Дизайн сайту", "Дизайн поліграфії", "Дизайн листівок і флаєрів", "Дизайн етикетки і пакування", "Дизайн буклетів", "Дизайн візиток", "Дизайн зовнішньої реклами", "Інше в дизайні поліграфії", "Послуги друку", "Друк на футболках", "Друк на чашках", "Друк поліграфії", "3D Друк", "Друк на полотні", "Друк на пластику і склі", "Інші послуги друку", "Малюнки та ілюстрації", "Дизайн банерів", "3D-дизайн", "3D Візуалізація", "3D Моделювання", "3D Графіка", "3D Анімація", "2D Анімація", "Інше в 3D-дизайні", "Розробка інфографіки", "UX/UI дизайн", "Інше в дизайні"],
"Робота в Інтернеті": ["Копірайтинг", "Збір, пошук інформації", "Наповнення сайтів", "Набір тексту", "Рерайтінг", "Введення даних", "Розшифровка інтерв'ю", "Створення презентацій", "Інша онлайн робота"],
"Реклама і маркетинг": ["Реклама в Інтернеті", "Реклама в соціальних мережах", "Розміщення оголошень", "Налаштування контекстної реклами", "SEO оптимізація сайту", "Розміщення постів на форумах", "SEO аудит сайту", "Просування сайтів", "Email-маркетинг", "Інша реклама в Інтернеті", "Поширення реклами", "Роздача флаєрів", "Розклеювання оголошень", "Реклама в поштові скриньки", "Реклама в сендвіч-панелі", "Інше в розповсюдженні реклами", "Виготовлення та монтаж зовнішньої реклами", "Вивіски та банери", "Обклеювання плівкою оракал", "Таблички та вказівники", "Штендери", "Лайтбокси та неонові вивіски", "Білборди", "Промо-стійки і стенди", "Об'ємні літери", "Виготовлення іншої зовнішньої реклами", "Послуги промоутерів", "Промоутери на промоакції", "Промоутер в супермаркет", "Соціологічні опитування", "Таємний покупець", "Масовка", "Послуги актора", "Промоутери в ростових ляльках", "Промо модель", "Мерчендайзер", "Послуги хостес", "Інші промоутери", "Послуги звукорежисера", "Звукорежисер", "Виготовлення аудіороликів", "Дикторське озвучування", "Аранжування, зведення та мастеринг", "Інші послуги звукозапису", "Послуги моделі", "Інша реклама"],
"Розробка сайтів та додатків": ["Створення сайтів", "Доробка сайту", "Створення Landing page", "Верстка сайту", "Тестування ПЗ (QA)", "Впровадження 1C", "Встановлення 1С", "Доопрацювання 1С", "Налаштування 1С", "Синхронізація з 1С", "Обслуговування 1С", "Оновлення 1С", "Інше у впровадженні 1С", "Послуги в сфері IT", "Розробка ПЗ", "Парсинг", "Скрипти і боти", "Адміністрування серверів", "Інші послуги в сфері IT", "Розробка мобільних додатків", "Додатки під iOS", "Додатки під Android", "Інше в розробці мобільних додатків", "Розробка ігор", "Створення та розробка технічного завдання", "Інші роботи з розробки сайтів"],
"Послуги для тварин": ["Догляд за котами", "Перетримка котів", "Стрижка котів", "Миття котів", "Підготовка котів до виставки", "Інший догляд за котами", "Догляд за собаками", "Вигул собак", "Перетримка собак", "Стрижка собак", "Навчання і дресирування собак", "Миття собак", "Підготовка собак до виставки", "Чистка зубів", "Вичісування собак", "Інший догляд за собаками", "Готель для тварин", "Перевезення тварин", "Догляд за рибками", "Чистка акваріумів", "Ремонт акваріумів", "Інший догляд за рибками", "Догляд за гризунами", "Догляд за птахами", "Перетримка птахів", "Підрізання дзьоба і кігтів", "Інший догляд за птахами", "Догляд за рептиліями", "Онлайн консультація ветеринара", "Інші зоопослуги"],
"Бюро перекладів": ["Письмові переклади", "Редактура перекладу", "Переклад документів та нотаріальне завірення", "Усні переклади", "Технічний переклад", "Переклад веб-сайтів", "Переклад аудіо та відео", "Апостиль і легалізація", "Інший переклад"],
"Організація свят": ["Послуги ведучого", "Тамада", "Ведучий на весілля", "Ведучий для ділових заходів", "Ведучий на День народження", "Ведучий на корпоратив", "Ведучий на випускний", "Ведучий на Новий рік", "Інші ведучі", "Музичний супровід", "Жива музика", "Запрошення DJ", "Інше в музичному супроводі", "Послуги аніматорів", "Аніматори для дітей", "Дід Мороз і Снігуронька", "Фокусник", "Клоун", "Аквагрим", "Майстер-класи", "Інші послуги аніматорів", "Організація харчування", "Банкет", "Організація пікніка", "Кейтеринг", "Фуршет", "Виїзний кава-брейк", "Інше в організації харчування", "Випічка та десерти", "Торти на замовлення", "Кенді бар", "Капкейки і тістечка", "Печиво і пряники", "Здобна випічка", "Інша випічка та десерти", "Персонал для заходів", "Офіціант", "Бармен", "Кальянщик", "Бариста", "Інший персонал для заходів", "Оформлення свят", "Флористика", "Оформлення повітряними кулями", "Декор для свят", "Весільний декор", "Реквізити для фотосесії", "Інше оформлення приміщень", "Свято під ключ", "Корпоративні заходи", "Приватні заходи", "Масові заходи", "Ділові заходи", "Інше свято під ключ", "Інші івент послуги"],
"Послуги репетиторів": ["Викладачі з предметів", "Репетитори з математики", "Репетитор з інформатики", "Репетитор з вищої математики", "Репетитори для підготовки до школи", "Репетитор з геометрії", "Репетитори для початкової школи", "Репетитор з алгебри", "Репетитор з програмування", "Репетитори з фізики", "Логопед", "Репетитор з історії", "Репетитор з географії", "Репетитор з біології", "Репетитор з літератури", "Репетитори з хімії", "Репетитори з малювання", "Репетитори з економіки", "Репетитор з макроекономіки", "Репетитор з нарисної геометрії", "Репетитори з опору матеріалів", "Репетитори з креслення", "Репетитори з філософії", "Репетитори з теоретичної механіки", "Репетитори з психології", "Репетитор з правознавства", "Репетитор з мікроекономіки", "Репетитор з менеджменту", "Інші викладачі предметів", "Репетитори з іноземних мов", "Репетитор англійської мови", "Англійська для дітей", "Репетитор німецької мови", "Репетитор української мови", "Репетитори з польської мови", "Репетитори з російської мови", "Репетитори з італійської мови", "Репетитор французької мови", "Репетитор іспанської мови", "Репетитори з японської мови", "Репетитори зі шведської мови", "Репетитори з чеської мови", "Репетитори білоруської мови", "Репетитори казахської мови", "Репетитори з хінді", "Репетитори з угорської мови", "Репетитори з фінської мови", "Репетитори з грецької мови", "Репетитори з турецької мови", "Репетитори румунської мови", "Репетитори з норвезької мови", "Репетитори з арабської мови", "Репетитори з латині", "Репетитори з корейської мови", "Репетитори з китайської мови", "Репетитори з нідерландської мови", "Репетитори з івриту", "Репетитори з данської мови", "Інші викладачі іноземних мов", "Написання робіт", "Реферати", "Курсові", "Дипломні", "Конспекти", "Контрольні", "Лабораторні", "Інше в написанні робіт", "Викладачі музики", "Репетитори з фортепіано", "Репетитори з сольфеджіо", "Репетитори з вокалу", "Репетитори з гітари", "Репетитори з гри на барабанах", "Репетитори з флейти", "Репетитори зі скрипки", "Репетитори з саксофону", "Інші викладачі музики", "Автоінструктори", "Водіння (АКПП)", "Водіння (МКПП)", "ПДР (теорія)", "Екстремальне водіння", "Водіння мотоцикла", "Пілотування", "Інше навчання водінню", "Інші репетитори", "Інші послуги репетиторів"],
"Послуги тренерів": ["Йога", "Раджа-йога", "Парна йога", "Йога танець Шиви", "Йога медитативні практики", "Йога дихальні практики", "Йога для вагітних", "Дитяча йога", "Бікрам-йога", "Хатха-йога", "Кундаліні-йога", "Йога Айенгара", "Інша йога", "Груповий фітнес", "Шейпінг", "Художня гімнастика", "Фітбол", "Стретчинг", "Бодіфлекс", "Ритміка", "Пілатес", "Калланетика", "Аеробіка", "Інший груповий фітнес", "Ігрові види спорту", "Футбол", "Фехтування", "Сквош", "Настільний теніс", "Легка атлетика", "Кінний спорт", "Гольф", "Волейбол", "Великий теніс", "Більярд", "Баскетбол", "Інші ігрові види спорту", "Водні види спорту", "Синхронне плавання", "Плавання", "Дайвінг", "Гребля", "Водне поло", "Аквааеробіка", "Інші водні види спорту", "Бойові мистецтва", "Тхеквондо", "Самбо", "Ушу", "Тайський бокс", "Рукопашний бій", "Кікбоксинг", "Карате", "Капоейра", "Дзюдо", "Джиу-джитсу", "Греко-римська боротьба", "Вільна боротьба", "Бокс", "Бої без правил", "Айкідо", "Інші бойові мистецтва", "Силові види спорту", "Важка атлетика", "Спортивна гімнастика", "Пауерліфтинг", "Кросфіт", "Бодібілдинг", "Акробатика", "Армрестлінг", "Інші силові види спорту", "Зимові види спорту", "Хокей", "Фігурне катання", "Сноуборд", "Гірські лижі", "Бігові лижі", "Інші зимові види спорту", "Хореографія", "Уроки з художньої гімнастики", "Уроки брейк-дансу", "Уроки стрип-пластики", "Уроки RnB (R&B)", "Уроки Хіп-хопу", "Уроки спортивних танців", "Народні танці", "Уроки латиноамериканських танців", "Уроки східних танців", "Уроки балету", "Інше в хореографії", "Інші види спорту", "Інші послуги тренерів"],
"Послуги краси і здоров'я": ["Масаж", "Загальний масаж", "Антицелюлітний масаж", "Лікувальний масаж", "Масаж спини", "Дитячий масаж", "Класичний масаж", "Масаж шийно-комірцевої зони", "Спортивний масаж", "Масаж ніг", "Масаж поперекової зони", "Масаж стоп", "Масаж живота", "Масаж рук", "Масаж обличчя", "Масаж голови", "Тайський масаж", "Інший масаж", "Догляд за нігтями", "Манікюр", "Педикюр", "Покриття гель-лаком", "Нарощування нігтів", "Корекція нігтів", "Інший догляд за нігтями", "Косметологія", "Догляд за віями", "Нарощування вій", "Корекція вій", "Фарбування вій", "Ламінування вій", "Біозавивка вій", "Інше в догляді за віями", "Догляд за бровами", "Корекція брів", "Фарбування брів", "Ламінування брів", "Мікроблейдинг брів", "Інший догляд за бровами", "Перманентний макіяж", "Перукарські послуги", "Стрижка", "Фарбування волосся", "Нарощування волосся", "Укладання волосся", "Хімічна завивка", "Полірування волосся", "Випрямлення і ламінування волосся", "Інші перукарські послуги", "Депіляція", "Депіляція воском", "Шугарінг", "Епіляція", "Інші послуги з видалення волосся", "Послуги візажиста-стиліста", "Макіяж", "Психолог", "Дієтолог", "Інший догляд за собою"],
"Ділові послуги": ["Бухгалтерські послуги", "Юридичні послуги", "Складання договорів", "Юридична консультація", "Послуги адвоката", "Послуги нотаріуса", "Послуги патентних повірених", "Реєстрація підприємств", "Ліквідація підприємств", "Складання та оформлення документів", "Складання та подання скарг, позовів", "Інші юридичні послуги", "Ріелтор", "Послуги колл-центру", "Фінансові послуги", "Консалтингові послуги", "Кадрові послуги", "Послуги безпеки", "Особиста охорона", "Послуги детектива", "Фізична охорона об'єктів", "Охорона і супровід вантажів", "Перевірка на детекторі брехні", "Інші послуги безпеки", "Послуги у сфері міграції", "Інші ділові послуги"],
"Ремонт авто": ["Допомога в дорозі", "Буксирування авто", "Доставка палива", "Евакуатор", "Зарядка акумулятора", "Заміна коліс", "Запуск двигуна", "Інша допомога в дорозі", "Технічне обслуговування та діагностика", "Автоелектрика", "Ремонт генераторів авто", "Послуги автоелектрика", "Встановлення автосигналізацій", "Монтаж магнітол і автозвуку", "Ремонт систем освітлення", "Кузовні роботи", "Кузовний ремонт", "Поклейка плівки", "Полірування авто", "Рихтування", "Фарбування авто", "Інші кузовні роботи", "Двигун", "Ремонт двигуна", "Діагностика двигуна", "Ремонт паливної системи", "Ремонт системи охолодження", "Ремонт турбін", "Інший ремонт двигуна", "Коробка перемикання передач", "Догляд за салоном", "Хімчистка салону", "Перетяжка салону авто", "Пошиття авточохлів", "Інший догляд за салоном", "Ремонт і заміна автоскла", "Ходова частина", "Рульова система", "Гальмівна система", "Вихлопна система", "Шиномонтаж", "Ремонт і обслуговування автокондиціонерів", "Встановлення газобалонного обладнання (ГБО)", "Ремонт мототехніки", "Автострахування", "Інший ремонт авто"],
"ІТ та програмування": ["Розробка веб-сайтів", "Мобільний додаток розробка", "Бази даних", "Системний адміністратор", "Кібербезпека", "QA тестування", "ІТ консультації", "ІТ аутсорсинг"],
"Медичні послуги": ["Лікар загальної практики", "Стоматологія", "Окуліст", "Фізіотерапія", "Психотерапія", "Лабораторні аналізи", "Медичний масаж", "Акупунктура", "Медичні консультації онлайн"],
"Організація подій": ["Весільне планування", "Корпоративні заходи", "Дитячі вечірки", "Фотограф", "Відеозйомка", "Декорації та дизайн", "Музикальне оформлення", "Ведучий подій", "Кейтеринг"],
"Освітні послуги": ["Приватні уроки", "Репетиторство", "Онлайн навчання", "Курси та тренінги", "Консультації з вибору професії", "Мовні курси", "Розвиваючі заняття для дітей", "Підготовка до іспитів"],
"Креативні послуги": ["Живопис", "Графічний дизайн", "Музичний виконавець", "Арт-терапія", "Театральне мистецтво", "Танці", "Літературне творчість", "Фотошоп та ретуш", "Робота з відео"],
"Консультаційні послуги": ["Юридичні консультації", "Фінансове планування", "Кар'єрне консультування", "Психологічна консультація", "Бізнес-консалтинг", "Медичні консультації", "Інтер'єрний дизайн", "Імідж-консультування"],
"Будівництво та ремонт": ["Будівництво нового житла", "Ремонт квартир", "Внутрішні роботи", "Зовнішні роботи", "Монтаж сантехніки", "Встановлення систем опалення", "Малярні роботи", "Ландшафтний дизайн", "Ремонт даху", "Буріння свердловин"],
"Спортивні послуги": ["Персональний тренер", "Групові тренування", "Йога", "Пілатес", "Фітнес-тренер", "Спортивний масаж", "Консультація з харчування", "Організація спортивних заходів", "Танцювальні заняття"],
"Технічна підтримка": ["Налаштування техніки", "Ремонт комп'ютерів", "Відновлення даних", "Обслуговування принтерів", "Налаштування мережі", "Видалення вірусів", "Консультації з ПЗ", "Робота з жорстким диском", "Апгрейд обладнання"],
"Автомобільні послуги": ["Автомобільний ремонт", "Технічне обслуговування", "Шиномонтаж", "Автомийка", "Діагностика двигуна", "Ремонт трансмісії", "Електричні роботи в автомобілі", "Послуги автомеханіка", "Ремонт гальмівної системи", "Виправлення кузова"],
"Харчові послуги": ["Кулінарні майстер-класи", "Приготування на замовлення", "Шеф-кухар на захід", "Організація кетерингу", "Дегустації та відгуки", "Консультації з харчування", "Постачання продуктів", "Смачна подорож"],
"Творчі послуги": ["Фотографія", "Відеозйомка", "Дизайн інтер'єру", "Музичний виконавець", "Літературне творчість", "Живопис та малювання", "Виготовлення виробів ручної роботи", "Кераміка та виробництво посуду", "Арт-терапія"],
"Подорожі та туризм": ["Туристичні послуги", "Бронювання готелів", "Трансфери та екскурсії", "Організація подорожей", "Путівки на курорти", "Індивідуальний гід", "Прокат автомобілів", "Мандрівки та походи"],
"Краса та догляд за собою": ["Парикмахерські послуги", "Манікюр та педикюр", "Косметологія", "Масаж та SPA-процедури", "Візаж та грим", "Стрижка та укладання волосся", "Солярій та загар", "Догляд за шкірою", "Епіляція та депіляція"],
"Еко-послуги": ["Впровадження екологічних технологій", "Садові та ландшафтні роботи", "Відновлення природних резерватів", "Екологічна консультація", "Рециклінг та утилізація", "Організація еко-подій", "Екотуризм та відпочинок"],
"Медіа та Комунікації": ["Створення відео контенту", "Редакція та коректура текстів", "Рекламна діяльність", "Піар та зв'язки з громадськістю", "Соціальні мережі та просування", "Тренінги голосу та дикції", "Телеведучий", "Створення та ведення блогу"],
"Сімейні послуги": ["Педіатрія та дитяча медицина", "Дитячий фотограф", "Дитячий психолог", "Родинний фотограф", "Допомога при народженні", "Консультації для батьків", "Сімейний фотоальбом", "Терапія для пар", "Педагогічні консультації"],
"Ігрові та розважальні послуги": ["Організація ігрових заходів", "Оренда ігрового обладнання", "Розважальні шоу та вистави", "Магія та ілюзії", "Тимбілдінг та корпоративи", "Квести та пригоди", "Веселі майстер-класи", "Анімація на дитячих святах", "Вечірки та дискотеки"]
}